<?xml version="1.0" encoding="UTF-8" standalone="no"?>
<databaseChangeLog xmlns="http://www.liquibase.org/xml/ns/dbchangelog"
	xmlns:xsi="http://www.w3.org/2001/XMLSchema-instance"
	xsi:schemaLocation="http://www.liquibase.org/xml/ns/dbchangelog
		http://www.liquibase.org/xml/ns/dbchangelog/dbchangelog-2.0.xsd">

	<changeSet author="seava" id="TBL-QRTZ_SIMPLE_TRIGGERS">
		<createTable tableName="QRTZ_SIMPLE_TRIGGERS">
			<column name="REPEAT_COUNT" type="int(10)">
				<constraints nullable="false"/>
			</column>
			<column name="REPEAT_INTERVAL" type="int(10)">
				<constraints nullable="false"/>
			</column>
			<column name="SCHED_NAME" type="varchar(255)">
				<constraints nullable="false"/>
			</column>
			<column name="TIMES_TRIGGERED" type="int(10)">
				<constraints nullable="false"/>
			</column>
			<column name="TRIGGER_GROUP" type="varchar(255)">
				<constraints nullable="false"/>
			</column>
			<column name="TRIGGER_NAME" type="varchar(255)">
				<constraints nullable="false"/>
			</column>
		</createTable>
	</changeSet>

	<changeSet author="seava" id="PK-QRTZ_SIMPLE_TRIGGERS">
		<addPrimaryKey 
			constraintName="PK_QRTZ_SIMPLE_TRIGGERS"
			tableName="QRTZ_SIMPLE_TRIGGERS"
			columnNames="SCHED_NAME,TRIGGER_NAME,TRIGGER_GROUP"/>
	</changeSet>

</databaseChangeLog>
